{
  "bookmarks" : [

  ],
  "fileId" : "dff6cf1f35ca7fe8a0c02422322791ca7bcda9ec0f03612497a528621958c12e",
  "highlights" : [

  ],
  "notes" : [
    {
      "body" : "test",
      "createdAt" : 792050435.656054,
      "highlightId" : "BF8D084A-7871-4CF3-96EF-226198910F9E",
      "id" : "488C6B2F-543C-4053-AB76-EBD2C5C3D088",
      "pdfBounds" : [
        [
          183.21735,
          155.32365
        ],
        [
          248.2114125,
          22.23585
        ]
      ],
      "pdfPageIndex" : 0,
      "title" : ""
    },
    {
      "body" : "Tbh agree with this",
      "createdAt" : 792052151.850848,
      "highlightId" : "2F5ECE82-F3BA-4F6F-90F0-6D64D1DCB885",
      "id" : "1C595709-12C5-4061-B740-1F8956CEB432",
      "pdfBounds" : [
        [
          216.52335,
          743.32365
        ],
        [
          271.412175,
          22.235850000000028
        ]
      ],
      "pdfPageIndex" : 1,
      "title" : ""
    }
  ],
  "pdfHighlights" : [
    {
      "bounds" : [
        [
          127.41352499999999,
          378.82365
        ],
        [
          80.24144999999999,
          22.23584999999997
        ]
      ],
      "colorHex" : "#FFD76A",
      "createdAt" : 792050431.720148,
      "id" : "4FAFC972-C6C0-40EF-A796-0203CE6D502C",
      "pageIndex" : 0
    },
    {
      "bounds" : [
        [
          183.21735,
          155.32365
        ],
        [
          248.2114125,
          22.23585
        ]
      ],
      "colorHex" : "#FFCC8C",
      "createdAt" : 792050435.655951,
      "id" : "BF8D084A-7871-4CF3-96EF-226198910F9E",
      "pageIndex" : 0
    },
    {
      "bounds" : [
        [
          216.52335,
          743.32365
        ],
        [
          271.412175,
          22.235850000000028
        ]
      ],
      "colorHex" : "#FFCC8C",
      "createdAt" : 792052151.850727,
      "id" : "2F5ECE82-F3BA-4F6F-90F0-6D64D1DCB885",
      "pageIndex" : 1
    }
  ],
  "updatedAt" : 792052367.482479
}